upkie_description/__init__.py
upkie_description/load_in_pinocchio.py
upkie_description/paths.py
upkie_description/meshes/ankle_stator.stl
upkie_description/meshes/knee_stator.stl
upkie_description/meshes/wheel_hub.stl
upkie_description/meshes/add-ons/camera_support.stl
upkie_description/meshes/add-ons/handle.stl
upkie_description/meshes/hollow_leg/hollow_femur.stl
upkie_description/meshes/hollow_leg/hollow_hip.stl
upkie_description/meshes/hollow_leg/hollow_knee.stl
upkie_description/meshes/mjbots/README.md
upkie_description/meshes/mjbots/mj5208_rotor.stl
upkie_description/meshes/mjbots/mj5208_stator.stl
upkie_description/meshes/mjbots/qdd100_horn.stl
upkie_description/meshes/mjbots/qdd100_rotor.stl
upkie_description/meshes/mjbots/qdd100_stator.stl
upkie_description/meshes/wheel_tire/README.md
upkie_description/meshes/wheel_tire/wheel_tire.stl
upkie_description/urdf/upkie.urdf
upkie_description/urdf/upkie_camera.urdf
upkie_description-2.2.0.dist-info/WHEEL
upkie_description-2.2.0.dist-info/METADATA
upkie_description-2.2.0.dist-info/RECORD
