Metadata-Version: 2.1
Name: upkie_description
Version: 2.2.0
Summary: URDF description for the Upkie wheeled biped.
Author-email: Stéphane Caron <stephane.caron@normalesup.org>
Maintainer-email: Stéphane Caron <stephane.caron@normalesup.org>
Requires-Python: >=3.7
Classifier: Development Status :: 5 - Production/Stable
Classifier: Intended Audience :: Developers
Classifier: Intended Audience :: Science/Research
Classifier: License :: OSI Approved :: Apache Software License
Classifier: Operating System :: OS Independent
Classifier: Programming Language :: Python :: 3.7
Classifier: Programming Language :: Python :: 3.8
Classifier: Programming Language :: Python :: 3.9
Classifier: Programming Language :: Python :: 3.10
Classifier: Programming Language :: Python :: 3.11
Classifier: Topic :: Scientific/Engineering :: Mathematics
Classifier: Topic :: Scientific/Engineering :: Physics
Project-URL: Changelog, https://github.com/upkie/upkie_description/blob/master/CHANGELOG.md
Project-URL: Source, https://github.com/upkie/upkie_description
Project-URL: Tracker, https://github.com/upkie/upkie_description/issues
